async_firmata
