Metadata-Version: 2.1
Name: async-firmata
Version: 0.0.2
Summary: An asynchronous interface for the Firmata protocol
Home-page: https://github.com/lennart-k/python-async-firmata
Author: Lennart K
License: UNKNOWN
Platform: UNKNOWN
Classifier: Programming Language :: Python :: 3.6
Classifier: License :: OSI Approved :: MIT License
Classifier: Operating System :: OS Independent
